asa/__init__.py
asa/core/__init__.py
asa/core/adapter.py
asa/core/bot.py
asa/core/condition.py
asa/core/config.py
asa/core/ctx.py
asa/core/deco.py
asa/core/discovery.py
asa/core/event.py
asa/core/logging.py
asa/plugin/__init__.py
asa/plugin/config.py
asa/plugin/type.py
asabot-0.1.4.dist-info/METADATA
asabot-0.1.4.dist-info/WHEEL
asabot-0.1.4.dist-info/licenses/LICENSE
asabot-0.1.4.dist-info/RECORD
