Metadata-Version: 2.4
Name: asabot
Version: 0.1.4
Summary: A napcat python sdk, easy for use
Author-email: isyuah <isyuah@outlook.com>
License: MIT
License-File: LICENSE
Classifier: License :: OSI Approved :: MIT License
Classifier: Operating System :: OS Independent
Classifier: Programming Language :: Python :: 3
Classifier: Programming Language :: Python :: 3 :: Only
Requires-Python: >=3.13
Requires-Dist: aiohttp>=3.13.2
Requires-Dist: loguru>=0.7.0
Provides-Extra: dev
Requires-Dist: pytest; extra == 'dev'
